ngscrape/__init__.py
ngscrape-3.0.3.dist-info/LICENSE
ngscrape-3.0.3.dist-info/METADATA
ngscrape-3.0.3.dist-info/WHEEL
ngscrape-3.0.3.dist-info/top_level.txt
ngscrape-3.0.3.dist-info/RECORD
