Metadata-Version: 2.1
Name: ngscrape
Version: 3.0.3
Summary: Newgrounds flash game scraper powered by bs4 and requests
Author-email: aeiea <dpthn@proton.me>
License: GNU AFFERO GENERAL PUBLIC LICENSE
Project-URL: Homepage, https://github.com/aeiea/ngscrape
Keywords: flash,newgrounds,scraper,games,opensource
Classifier: License :: OSI Approved :: GNU Affero General Public License v3 or later (AGPLv3+)
Classifier: Programming Language :: Python
Classifier: Programming Language :: Python :: 3
Requires-Python: >=3.0
License-File: LICENSE
Requires-Dist: beautifulsoup4
Requires-Dist: requests
